[
    {
        "id": 1,
        "name": "Beckaroo & The Zoo",
        "tools": [
            {
                "tool": "JavaScript",
                "color": "badge-warning"
            },
            {
                "tool": "React",
                "color": "badge-info"
            },
            {
                "tool": "Tailwindcss",
                "color": "badge-secondary"
            },
            {
                "tool": "Supabase",
                "color": "badge-success"
            }
        ],
        "description": "Lorem ipsum dolor sit amet, consectetur adipiscing elit. Duis non nisi eget ipsum lacinia varius et maximus magna. Sed hendrerit purus imperdiet elementum condimentum. Mauris cursus sagittis iaculis.",
        "url": "https://google.com",
        "github": "https://github.com/PurpleTurtl04/Portfolio",
        "image": "/images/Beckaroo.png"
    },
    {
        "id": 2,
        "name": "ChatApp",
        "tools": [
            {
                "tool": "JavaScript",
                "color": "badge-warning"
            },
            {
                "tool": "React",
                "color": "badge-info"
            },
            {
                "tool": "Tailwindcss",
                "color": "badge-secondary"
            },
            {
                "tool": "Vite",
                "color": "badge-primary"
            }
        ],
        "description": "Lorem ipsum dolor sit amet, consectetur adipiscing elit. Duis non nisi eget ipsum lacinia varius et maximus magna. Sed hendrerit purus imperdiet elementum condimentum. Mauris cursus sagittis iaculis.",
        "url": "https://google.com",
        "github": "https://github.com/PurpleTurtl04/ChatApp",
        "image": "/images/Beckaroo.png"
    },
    {
        "id": 3,
        "name": "Team App",
        "tools": [
            {
                "tool": "JavaScript",
                "color": "badge-warning"
            },
            {
                "tool": "React",
                "color": "badge-info"
            },
            {
                "tool": "Tailwindcss",
                "color": "badge-secondary"
            },
            {
                "tool": "Vite",
                "color": "badge-primary"
            }
        ],
        "description": "Lorem ipsum dolor sit amet, consectetur adipiscing elit. Duis non nisi eget ipsum lacinia varius et maximus magna. Sed hendrerit purus imperdiet elementum condimentum. Mauris cursus sagittis iaculis.",
        "url": "https://google.com",
        "github": "https://github.com/PurpleTurtl04/Team-App",
        "image": "/images/Beckaroo.png"
    },
    {
        "id": 4,
        "name": "Beckaroo & The Zoo",
        "tools": [
            {
                "tool": "JavaScript",
                "color": "badge-warning"
            },
            {
                "tool": "React",
                "color": "badge-info"
            },
            {
                "tool": "Tailwindcss",
                "color": "badge-secondary"
            },
            {
                "tool": "Supabase",
                "color": "badge-success"
            }
        ],
        "description": "Lorem ipsum dolor sit amet, consectetur adipiscing elit. Duis non nisi eget ipsum lacinia varius et maximus magna. Sed hendrerit purus imperdiet elementum condimentum. Mauris cursus sagittis iaculis.",
        "url": "https://google.com",
        "github": "https://github.com/PurpleTurtl04/Portfolio",
        "image": "/images/Beckaroo.png"
    }
]
